encryptcontent/__init__.py
encryptcontent/canary.tpl.py
encryptcontent/decrypt-contents.tpl.js
encryptcontent/decrypt-form.tpl.html
encryptcontent/plugin - Kopie.py
encryptcontent/plugin.py
encryptcontent/contrib/templates/search/lunr.js
encryptcontent/contrib/templates/search/main.js
encryptcontent/contrib/templates/search/worker.js
mkdocs_encryptcontent_plugin-3.1.0.dist-info/LICENSE.md
mkdocs_encryptcontent_plugin-3.1.0.dist-info/METADATA
mkdocs_encryptcontent_plugin-3.1.0.dist-info/WHEEL
mkdocs_encryptcontent_plugin-3.1.0.dist-info/entry_points.txt
mkdocs_encryptcontent_plugin-3.1.0.dist-info/top_level.txt
mkdocs_encryptcontent_plugin-3.1.0.dist-info/RECORD
