Metadata-Version: 2.1
Name: mkdocs-encryptcontent-plugin
Version: 3.1.0
Summary: A MkDocs plugin that encrypt/decrypt markdown content with AES
Home-page: https://unverbuggt.github.io/mkdocs-encryptcontent-plugin/
Author: unverbuggt
Author-email: unverbuggt@xn--rthlein-n2a.de
License: MIT
Keywords: mkdocs python markdown encrypt decrypt content
Classifier: Development Status :: 5 - Production/Stable
Classifier: Intended Audience :: Developers
Classifier: Intended Audience :: Information Technology
Classifier: License :: OSI Approved :: MIT License
Classifier: Programming Language :: Python
Classifier: Programming Language :: Python :: 3.5
Classifier: Programming Language :: Python :: 3.6
Classifier: Programming Language :: Python :: 3.7
Classifier: Programming Language :: Python :: 3.8
Classifier: Programming Language :: Python :: 3.9
Classifier: Programming Language :: Python :: 3.10
Requires-Python: >=3.5
License-File: LICENSE.md
